smtools/__init__.py
smtools/alignment.py
smtools/curtains.py
smtools/misc.py
smtools/point_fitting.py
smtools/testdata/10_align.tif
smtools/testdata/11_align.tif
smtools/testdata/1_align.tif
smtools/testdata/2_align.tif
smtools/testdata/3_align.tif
smtools/testdata/4_align.tif
smtools/testdata/5_align.tif
smtools/testdata/6_align.tif
smtools/testdata/7_align.tif
smtools/testdata/8_align.tif
smtools/testdata/9_align.tif
smtools/testdata/__init__.py
smtools/testdata/single_max.tif
smtools/testdata/test_curtain.tif
smtools-0.2.2.dist-info/LICENSE
smtools-0.2.2.dist-info/METADATA
smtools-0.2.2.dist-info/WHEEL
smtools-0.2.2.dist-info/top_level.txt
smtools-0.2.2.dist-info/RECORD
