Metadata-Version: 2.1
Name: smtools
Version: 0.2.2
Summary: Redding Lab analysis tools
Home-page: https://github.com/ReddingLab/smtools
Author: Sy Redding
Author-email: UNKNOWN
License: UNKNOWN
Platform: UNKNOWN
Classifier: Programming Language :: Python :: 3
Classifier: License :: OSI Approved :: MIT License
Classifier: Operating System :: OS Independent
Requires-Dist: numpy
Requires-Dist: scipy
Requires-Dist: scikit-image
Requires-Dist: matplotlib
